{
  "nodes": [
    {
      "id": "region-us-east-2",
      "type": "resourceNode",
      "position": {
        "x": -40,
        "y": -40
      },
      "data": {
        "label": "Region: us-east-2",
        "resourceType": {
          "id": "region",
          "name": "Region",
          "category": "networking",
          "icon": "vpc",
          "description": "AWS Region",
          "color": "#3949AB",
          "editableAttributes": [
            {
              "key": "label",
              "label": "Region Name",
              "type": "text"
            },
            {
              "key": "region",
              "label": "Region Code",
              "type": "text"
            }
          ]
        },
        "region": "us-east-2",
        "isContainer": true,
        "width": 100,
        "height": 100,
        "size": {
          "width": 2000,
          "height": 730
        },
        "config": {
          "originalType": "AWS::EC2::Region",
          "region": "us-east-2"
        },
        "nestingDepth": 0,
        "parentId": null
      },
      "width": 2000,
      "height": 730
    },
    {
      "id": "vpc-vpc-06cc31a57a405feb8",
      "type": "resourceNode",
      "position": {
        "x": -20,
        "y": -20
      },
      "data": {
        "label": "vpc-06cc31a57a405feb8",
        "resourceType": {
          "id": "vpc",
          "name": "VPC",
          "category": "networking",
          "icon": "vpc",
          "description": "Virtual Private Cloud",
          "color": "#8C4FFF",
          "editableAttributes": [
            {
              "key": "vpcName",
              "label": "VPC Name",
              "type": "text",
              "placeholder": "my-vpc"
            },
            {
              "key": "cidrBlock",
              "label": "CIDR Block",
              "type": "text",
              "placeholder": "10.0.0.0/16"
            }
          ]
        },
        "vpcId": "vpc-06cc31a57a405feb8",
        "cidrBlock": "10.0.0.0/16",
        "state": "available",
        "isDefault": false,
        "isContainer": true,
        "size": {
          "width": 610,
          "height": 656
        },
        "config": {
          "originalType": "AWS::EC2::VPC",
          "region": "us-east-2",
          "ownerId": "720150001470",
          "instanceTenancy": "default",
          "dhcpOptionsId": "dopt-006475053db1b9fc4"
        },
        "nestingDepth": 1,
        "parentId": "region-us-east-2"
      },
      "width": 610,
      "height": 656
    },
    {
      "id": "vpc-vpc-0010db00d5f9b6d24",
      "type": "resourceNode",
      "position": {
        "x": 30,
        "y": 170
      },
      "data": {
        "label": "vpc-0010db00d5f9b6d24",
        "resourceType": {
          "id": "vpc",
          "name": "VPC",
          "category": "networking",
          "icon": "vpc",
          "description": "Virtual Private Cloud",
          "color": "#8C4FFF",
          "editableAttributes": [
            {
              "key": "vpcName",
              "label": "VPC Name",
              "type": "text",
              "placeholder": "my-vpc"
            },
            {
              "key": "cidrBlock",
              "label": "CIDR Block",
              "type": "text",
              "placeholder": "10.0.0.0/16"
            }
          ]
        },
        "vpcId": "vpc-0010db00d5f9b6d24",
        "cidrBlock": "172.31.0.0/16",
        "state": "available",
        "isDefault": true,
        "isContainer": true,
        "size": {
          "width": 1010,
          "height": 500
        },
        "config": {
          "originalType": "AWS::EC2::VPC",
          "region": "us-east-2",
          "ownerId": "720150001470",
          "instanceTenancy": "default",
          "dhcpOptionsId": "dopt-006475053db1b9fc4"
        },
        "nestingDepth": 1,
        "parentId": "region-us-east-2"
      },
      "width": 1010,
      "height": 500
    },
    {
      "id": "vpc-vpc-0b71e8dcdd9a40ef8",
      "type": "resourceNode",
      "position": {
        "x": 30,
        "y": 170
      },
      "data": {
        "label": "vpc-0b71e8dcdd9a40ef8",
        "resourceType": {
          "id": "vpc",
          "name": "VPC",
          "category": "networking",
          "icon": "vpc",
          "description": "Virtual Private Cloud",
          "color": "#8C4FFF",
          "editableAttributes": [
            {
              "key": "vpcName",
              "label": "VPC Name",
              "type": "text",
              "placeholder": "my-vpc"
            },
            {
              "key": "cidrBlock",
              "label": "CIDR Block",
              "type": "text",
              "placeholder": "10.0.0.0/16"
            }
          ]
        },
        "vpcId": "vpc-0b71e8dcdd9a40ef8",
        "cidrBlock": "10.0.0.0/16",
        "state": "available",
        "isDefault": false,
        "isContainer": true,
        "size": {
          "width": 1460,
          "height": 466
        },
        "config": {
          "originalType": "AWS::EC2::VPC",
          "region": "us-east-2",
          "ownerId": "720150001470",
          "instanceTenancy": "default",
          "dhcpOptionsId": "dopt-006475053db1b9fc4"
        },
        "nestingDepth": 1,
        "parentId": "region-us-east-2"
      },
      "width": 1460,
      "height": 466
    },
    {
      "id": "vpc-vpc-0eb8eab8fc060589d",
      "type": "resourceNode",
      "position": {
        "x": 30,
        "y": 170
      },
      "data": {
        "label": "vpc-0eb8eab8fc060589d",
        "resourceType": {
          "id": "vpc",
          "name": "VPC",
          "category": "networking",
          "icon": "vpc",
          "description": "Virtual Private Cloud",
          "color": "#8C4FFF",
          "editableAttributes": [
            {
              "key": "vpcName",
              "label": "VPC Name",
              "type": "text",
              "placeholder": "my-vpc"
            },
            {
              "key": "cidrBlock",
              "label": "CIDR Block",
              "type": "text",
              "placeholder": "10.0.0.0/16"
            }
          ]
        },
        "vpcId": "vpc-0eb8eab8fc060589d",
        "cidrBlock": "10.0.0.0/16",
        "state": "available",
        "isDefault": false,
        "isContainer": true,
        "size": {
          "width": 1910,
          "height": 466
        },
        "config": {
          "originalType": "AWS::EC2::VPC",
          "region": "us-east-2",
          "ownerId": "720150001470",
          "instanceTenancy": "default",
          "dhcpOptionsId": "dopt-006475053db1b9fc4"
        },
        "nestingDepth": 1,
        "parentId": "region-us-east-2"
      },
      "width": 1910,
      "height": 466
    },
    {
      "id": "subnet-subnet-0d7e95372896d77e8",
      "type": "resourceNode",
      "position": {
        "x": 580,
        "y": 190
      },
      "data": {
        "label": "subnet-0d7e95372896d77e8",
        "resourceType": {
          "id": "subnet",
          "name": "Subnet",
          "category": "networking",
          "icon": "vpc",
          "description": "Virtual Subnet",
          "color": "#8C4FFF",
          "editableAttributes": [
            {
              "key": "label",
              "label": "Subnet ID",
              "type": "text"
            },
            {
              "key": "cidrBlock",
              "label": "CIDR Block",
              "type": "text"
            }
          ]
        },
        "subnetId": "subnet-0d7e95372896d77e8",
        "vpcId": "vpc-0010db00d5f9b6d24",
        "cidrBlock": "172.31.0.0/20",
        "availabilityZone": "us-east-2a",
        "state": "available",
        "isContainer": true,
        "size": {
          "width": 200,
          "height": 80
        },
        "config": {
          "originalType": "AWS::EC2::Subnet",
          "region": "us-east",
          "ownerId": "720150001470",
          "availabilityZoneId": "use2-az1",
          "defaultForAz": true
        },
        "nestingDepth": 2,
        "parentId": "vpc-vpc-0010db00d5f9b6d24"
      },
      "width": 200,
      "height": 80
    },
    {
      "id": "subnet-subnet-0f74cb72353a2b237",
      "type": "resourceNode",
      "position": {
        "x": 580,
        "y": 380
      },
      "data": {
        "label": "subnet-0f74cb72353a2b237",
        "resourceType": {
          "id": "subnet",
          "name": "Subnet",
          "category": "networking",
          "icon": "vpc",
          "description": "Virtual Subnet",
          "color": "#8C4FFF",
          "editableAttributes": [
            {
              "key": "label",
              "label": "Subnet ID",
              "type": "text"
            },
            {
              "key": "cidrBlock",
              "label": "CIDR Block",
              "type": "text"
            }
          ]
        },
        "subnetId": "subnet-0f74cb72353a2b237",
        "vpcId": "vpc-0010db00d5f9b6d24",
        "cidrBlock": "172.31.16.0/20",
        "availabilityZone": "us-east-2b",
        "state": "available",
        "isContainer": true,
        "size": {
          "width": 200,
          "height": 80
        },
        "config": {
          "originalType": "AWS::EC2::Subnet",
          "region": "us-east",
          "ownerId": "720150001470",
          "availabilityZoneId": "use2-az2",
          "defaultForAz": true
        },
        "nestingDepth": 2,
        "parentId": "vpc-vpc-0010db00d5f9b6d24"
      },
      "width": 200,
      "height": 80
    },
    {
      "id": "subnet-subnet-0caaa7cee2f392f8d",
      "type": "resourceNode",
      "position": {
        "x": 580,
        "y": 570
      },
      "data": {
        "label": "subnet-0caaa7cee2f392f8d",
        "resourceType": {
          "id": "subnet",
          "name": "Subnet",
          "category": "networking",
          "icon": "vpc",
          "description": "Virtual Subnet",
          "color": "#8C4FFF",
          "editableAttributes": [
            {
              "key": "label",
              "label": "Subnet ID",
              "type": "text"
            },
            {
              "key": "cidrBlock",
              "label": "CIDR Block",
              "type": "text"
            }
          ]
        },
        "subnetId": "subnet-0caaa7cee2f392f8d",
        "vpcId": "vpc-0010db00d5f9b6d24",
        "cidrBlock": "172.31.32.0/20",
        "availabilityZone": "us-east-2c",
        "state": "available",
        "isContainer": true,
        "size": {
          "width": 200,
          "height": 80
        },
        "config": {
          "originalType": "AWS::EC2::Subnet",
          "region": "us-east",
          "ownerId": "720150001470",
          "availabilityZoneId": "use2-az3",
          "defaultForAz": true
        },
        "nestingDepth": 2,
        "parentId": "vpc-vpc-0010db00d5f9b6d24"
      },
      "width": 200,
      "height": 80
    },
    {
      "id": "subnet-subnet-0cc22aef01a024a4a",
      "type": "resourceNode",
      "position": {
        "x": 1480,
        "y": 190
      },
      "data": {
        "label": "subnet-0cc22aef01a024a4a",
        "resourceType": {
          "id": "subnet",
          "name": "Subnet",
          "category": "networking",
          "icon": "vpc",
          "description": "Virtual Subnet",
          "color": "#8C4FFF",
          "editableAttributes": [
            {
              "key": "label",
              "label": "Subnet ID",
              "type": "text"
            },
            {
              "key": "cidrBlock",
              "label": "CIDR Block",
              "type": "text"
            }
          ]
        },
        "subnetId": "subnet-0cc22aef01a024a4a",
        "vpcId": "vpc-0eb8eab8fc060589d",
        "cidrBlock": "10.0.2.0/24",
        "availabilityZone": "us-east-2b",
        "state": "available",
        "isContainer": true,
        "size": {
          "width": 200,
          "height": 80
        },
        "config": {
          "originalType": "AWS::EC2::Subnet",
          "region": "us-east",
          "ownerId": "720150001470",
          "availabilityZoneId": "use2-az2",
          "defaultForAz": false
        },
        "nestingDepth": 2,
        "parentId": "vpc-vpc-0eb8eab8fc060589d"
      },
      "width": 200,
      "height": 80
    },
    {
      "id": "subnet-subnet-01c723a4e0cd68d4f",
      "type": "resourceNode",
      "position": {
        "x": 1480,
        "y": 380
      },
      "data": {
        "label": "subnet-01c723a4e0cd68d4f",
        "resourceType": {
          "id": "subnet",
          "name": "Subnet",
          "category": "networking",
          "icon": "vpc",
          "description": "Virtual Subnet",
          "color": "#8C4FFF",
          "editableAttributes": [
            {
              "key": "label",
              "label": "Subnet ID",
              "type": "text"
            },
            {
              "key": "cidrBlock",
              "label": "CIDR Block",
              "type": "text"
            }
          ]
        },
        "subnetId": "subnet-01c723a4e0cd68d4f",
        "vpcId": "vpc-0eb8eab8fc060589d",
        "cidrBlock": "10.0.1.0/24",
        "availabilityZone": "us-east-2a",
        "state": "available",
        "isContainer": true,
        "size": {
          "width": 200,
          "height": 80
        },
        "config": {
          "originalType": "AWS::EC2::Subnet",
          "region": "us-east",
          "ownerId": "720150001470",
          "availabilityZoneId": "use2-az1",
          "defaultForAz": false
        },
        "nestingDepth": 2,
        "parentId": "vpc-vpc-0eb8eab8fc060589d"
      },
      "width": 200,
      "height": 80
    },
    {
      "id": "subnet-subnet-0da1a05dfc8b55dc3",
      "type": "resourceNode",
      "position": {
        "x": 130,
        "y": 190
      },
      "data": {
        "label": "subnet-0da1a05dfc8b55dc3",
        "resourceType": {
          "id": "subnet",
          "name": "Subnet",
          "category": "networking",
          "icon": "vpc",
          "description": "Virtual Subnet",
          "color": "#8C4FFF",
          "editableAttributes": [
            {
              "key": "label",
              "label": "Subnet ID",
              "type": "text"
            },
            {
              "key": "cidrBlock",
              "label": "CIDR Block",
              "type": "text"
            }
          ]
        },
        "subnetId": "subnet-0da1a05dfc8b55dc3",
        "vpcId": "vpc-06cc31a57a405feb8",
        "cidrBlock": "10.0.1.0/24",
        "availabilityZone": "us-east-2a",
        "state": "available",
        "isContainer": true,
        "size": {
          "width": 165,
          "height": 193
        },
        "config": {
          "originalType": "AWS::EC2::Subnet",
          "region": "us-east",
          "ownerId": "720150001470",
          "availabilityZoneId": "use2-az1",
          "defaultForAz": false
        },
        "nestingDepth": 2,
        "parentId": "vpc-vpc-06cc31a57a405feb8"
      },
      "width": 165,
      "height": 193
    },
    {
      "id": "subnet-subnet-09a9db2e951c22a88",
      "type": "resourceNode",
      "position": {
        "x": 130,
        "y": 423
      },
      "data": {
        "label": "subnet-09a9db2e951c22a88",
        "resourceType": {
          "id": "subnet",
          "name": "Subnet",
          "category": "networking",
          "icon": "vpc",
          "description": "Virtual Subnet",
          "color": "#8C4FFF",
          "editableAttributes": [
            {
              "key": "label",
              "label": "Subnet ID",
              "type": "text"
            },
            {
              "key": "cidrBlock",
              "label": "CIDR Block",
              "type": "text"
            }
          ]
        },
        "subnetId": "subnet-09a9db2e951c22a88",
        "vpcId": "vpc-06cc31a57a405feb8",
        "cidrBlock": "10.0.2.0/24",
        "availabilityZone": "us-east-2b",
        "state": "available",
        "isContainer": true,
        "size": {
          "width": 200,
          "height": 80
        },
        "config": {
          "originalType": "AWS::EC2::Subnet",
          "region": "us-east",
          "ownerId": "720150001470",
          "availabilityZoneId": "use2-az2",
          "defaultForAz": false
        },
        "nestingDepth": 2,
        "parentId": "vpc-vpc-06cc31a57a405feb8"
      },
      "width": 200,
      "height": 80
    },
    {
      "id": "subnet-subnet-0381aa2076a4bb590",
      "type": "resourceNode",
      "position": {
        "x": 1030,
        "y": 190
      },
      "data": {
        "label": "subnet-0381aa2076a4bb590",
        "resourceType": {
          "id": "subnet",
          "name": "Subnet",
          "category": "networking",
          "icon": "vpc",
          "description": "Virtual Subnet",
          "color": "#8C4FFF",
          "editableAttributes": [
            {
              "key": "label",
              "label": "Subnet ID",
              "type": "text"
            },
            {
              "key": "cidrBlock",
              "label": "CIDR Block",
              "type": "text"
            }
          ]
        },
        "subnetId": "subnet-0381aa2076a4bb590",
        "vpcId": "vpc-0b71e8dcdd9a40ef8",
        "cidrBlock": "10.0.1.0/24",
        "availabilityZone": "us-east-2a",
        "state": "available",
        "isContainer": true,
        "size": {
          "width": 200,
          "height": 80
        },
        "config": {
          "originalType": "AWS::EC2::Subnet",
          "region": "us-east",
          "ownerId": "720150001470",
          "availabilityZoneId": "use2-az1",
          "defaultForAz": false
        },
        "nestingDepth": 2,
        "parentId": "vpc-vpc-0b71e8dcdd9a40ef8"
      },
      "width": 200,
      "height": 80
    },
    {
      "id": "subnet-subnet-03f6049180d037062",
      "type": "resourceNode",
      "position": {
        "x": 1030,
        "y": 380
      },
      "data": {
        "label": "subnet-03f6049180d037062",
        "resourceType": {
          "id": "subnet",
          "name": "Subnet",
          "category": "networking",
          "icon": "vpc",
          "description": "Virtual Subnet",
          "color": "#8C4FFF",
          "editableAttributes": [
            {
              "key": "label",
              "label": "Subnet ID",
              "type": "text"
            },
            {
              "key": "cidrBlock",
              "label": "CIDR Block",
              "type": "text"
            }
          ]
        },
        "subnetId": "subnet-03f6049180d037062",
        "vpcId": "vpc-0b71e8dcdd9a40ef8",
        "cidrBlock": "10.0.2.0/24",
        "availabilityZone": "us-east-2b",
        "state": "available",
        "isContainer": true,
        "size": {
          "width": 200,
          "height": 80
        },
        "config": {
          "originalType": "AWS::EC2::Subnet",
          "region": "us-east",
          "ownerId": "720150001470",
          "availabilityZoneId": "use2-az2",
          "defaultForAz": false
        },
        "nestingDepth": 2,
        "parentId": "vpc-vpc-0b71e8dcdd9a40ef8"
      },
      "width": 200,
      "height": 80
    },
    {
      "id": "instance-i-0525e04aaef702279",
      "type": "resourceNode",
      "position": {
        "x": 155,
        "y": 275
      },
      "data": {
        "label": "blazeops-agent-staging-backend-api",
        "resourceType": {
          "id": "ec2",
          "name": "EC2 Instance",
          "category": "compute",
          "icon": "ec2",
          "description": "Elastic Compute Cloud",
          "color": "#FF9900",
          "editableAttributes": [
            {
              "key": "label",
              "label": "Instance ID",
              "type": "text"
            },
            {
              "key": "instanceType",
              "label": "Instance Type",
              "type": "text"
            }
          ]
        },
        "instanceId": "i-0525e04aaef702279",
        "instanceType": "t3.small",
        "state": "running",
        "privateIpAddress": "10.0.1.119",
        "publicIpAddress": "3.142.252.53",
        "imageId": "ami-0e83be366243f524a",
        "launchTime": "2025-11-20T13:09:30+00:00",
        "subnetId": "subnet-0da1a05dfc8b55dc3",
        "vpcId": "vpc-06cc31a57a405feb8",
        "securityGroup": "sg-0c7910417aebd89b9",
        "isContainer": false,
        "size": {
          "width": 120,
          "height": 88
        },
        "config": {
          "originalType": "AWS::EC2::Instance",
          "region": "0da1a05dfc8b55dc3",
          "vpc": "vpc-06cc31a57a405feb8",
          "subnet": "subnet-0da1a05dfc8b55dc3",
          "securityGroup": "sg-0c7910417aebd89b9",
          "instanceType": "t3.small",
          "architecture": "x86_64",
          "hypervisor": "xen",
          "virtualizationType": "hvm",
          "rootDeviceName": "/dev/sda1",
          "rootDeviceType": "ebs",
          "keyName": "blazeops-agent-staging-ec2-key"
        },
        "nestingDepth": 3,
        "parentId": "subnet-subnet-0da1a05dfc8b55dc3"
      },
      "width": 120,
      "height": 88
    },
    {
      "id": "rt-rtb-01acacde45952b958",
      "type": "resourceNode",
      "position": {
        "x": 450,
        "y": 390
      },
      "data": {
        "label": "rtb-01acacde45952b958",
        "resourceType": {
          "id": "routetable",
          "name": "Route Table",
          "category": "networking",
          "icon": "vpc",
          "description": "Route Table",
          "color": "#8C4FFF",
          "editableAttributes": [
            {
              "key": "label",
              "label": "Route Table ID",
              "type": "text"
            }
          ]
        },
        "routeTableId": "rtb-01acacde45952b958",
        "vpcId": "vpc-06cc31a57a405feb8",
        "isContainer": false,
        "size": {
          "width": 120,
          "height": 88
        },
        "config": {
          "originalType": "AWS::EC2::RouteTable",
          "region": "06cc31a57a405feb8",
          "vpcId": "vpc-06cc31a57a405feb8",
          "ownerId": "720150001470"
        },
        "nestingDepth": 2,
        "parentId": "vpc-vpc-06cc31a57a405feb8"
      },
      "width": 120,
      "height": 88
    },
    {
      "id": "rt-rtb-0f5539d37304dfe0a",
      "type": "resourceNode",
      "position": {
        "x": 450,
        "y": 528
      },
      "data": {
        "label": "rtb-0f5539d37304dfe0a",
        "resourceType": {
          "id": "routetable",
          "name": "Route Table",
          "category": "networking",
          "icon": "vpc",
          "description": "Route Table",
          "color": "#8C4FFF",
          "editableAttributes": [
            {
              "key": "label",
              "label": "Route Table ID",
              "type": "text"
            }
          ]
        },
        "routeTableId": "rtb-0f5539d37304dfe0a",
        "vpcId": "vpc-06cc31a57a405feb8",
        "isContainer": false,
        "size": {
          "width": 120,
          "height": 88
        },
        "config": {
          "originalType": "AWS::EC2::RouteTable",
          "region": "06cc31a57a405feb8",
          "vpcId": "vpc-06cc31a57a405feb8",
          "ownerId": "720150001470"
        },
        "nestingDepth": 2,
        "parentId": "vpc-vpc-06cc31a57a405feb8"
      },
      "width": 120,
      "height": 88
    },
    {
      "id": "rt-rtb-09467ba9741ae03be",
      "type": "resourceNode",
      "position": {
        "x": 900,
        "y": 390
      },
      "data": {
        "label": "rtb-09467ba9741ae03be",
        "resourceType": {
          "id": "routetable",
          "name": "Route Table",
          "category": "networking",
          "icon": "vpc",
          "description": "Route Table",
          "color": "#8C4FFF",
          "editableAttributes": [
            {
              "key": "label",
              "label": "Route Table ID",
              "type": "text"
            }
          ]
        },
        "routeTableId": "rtb-09467ba9741ae03be",
        "vpcId": "vpc-0010db00d5f9b6d24",
        "isContainer": false,
        "size": {
          "width": 120,
          "height": 88
        },
        "config": {
          "originalType": "AWS::EC2::RouteTable",
          "region": "0010db00d5f9b6d24",
          "vpcId": "vpc-0010db00d5f9b6d24",
          "ownerId": "720150001470"
        },
        "nestingDepth": 2,
        "parentId": "vpc-vpc-0010db00d5f9b6d24"
      },
      "width": 120,
      "height": 88
    },
    {
      "id": "rt-rtb-051150827cea9acd3",
      "type": "resourceNode",
      "position": {
        "x": 1350,
        "y": 390
      },
      "data": {
        "label": "rtb-051150827cea9acd3",
        "resourceType": {
          "id": "routetable",
          "name": "Route Table",
          "category": "networking",
          "icon": "vpc",
          "description": "Route Table",
          "color": "#8C4FFF",
          "editableAttributes": [
            {
              "key": "label",
              "label": "Route Table ID",
              "type": "text"
            }
          ]
        },
        "routeTableId": "rtb-051150827cea9acd3",
        "vpcId": "vpc-0b71e8dcdd9a40ef8",
        "isContainer": false,
        "size": {
          "width": 120,
          "height": 88
        },
        "config": {
          "originalType": "AWS::EC2::RouteTable",
          "region": "0b71e8dcdd9a40ef8",
          "vpcId": "vpc-0b71e8dcdd9a40ef8",
          "ownerId": "720150001470"
        },
        "nestingDepth": 2,
        "parentId": "vpc-vpc-0b71e8dcdd9a40ef8"
      },
      "width": 120,
      "height": 88
    },
    {
      "id": "rt-rtb-04c6172af2a46c76f",
      "type": "resourceNode",
      "position": {
        "x": 1350,
        "y": 528
      },
      "data": {
        "label": "rtb-04c6172af2a46c76f",
        "resourceType": {
          "id": "routetable",
          "name": "Route Table",
          "category": "networking",
          "icon": "vpc",
          "description": "Route Table",
          "color": "#8C4FFF",
          "editableAttributes": [
            {
              "key": "label",
              "label": "Route Table ID",
              "type": "text"
            }
          ]
        },
        "routeTableId": "rtb-04c6172af2a46c76f",
        "vpcId": "vpc-0b71e8dcdd9a40ef8",
        "isContainer": false,
        "size": {
          "width": 120,
          "height": 88
        },
        "config": {
          "originalType": "AWS::EC2::RouteTable",
          "region": "0b71e8dcdd9a40ef8",
          "vpcId": "vpc-0b71e8dcdd9a40ef8",
          "ownerId": "720150001470"
        },
        "nestingDepth": 2,
        "parentId": "vpc-vpc-0b71e8dcdd9a40ef8"
      },
      "width": 120,
      "height": 88
    },
    {
      "id": "rt-rtb-02e5b59e28181011c",
      "type": "resourceNode",
      "position": {
        "x": 1800,
        "y": 390
      },
      "data": {
        "label": "rtb-02e5b59e28181011c",
        "resourceType": {
          "id": "routetable",
          "name": "Route Table",
          "category": "networking",
          "icon": "vpc",
          "description": "Route Table",
          "color": "#8C4FFF",
          "editableAttributes": [
            {
              "key": "label",
              "label": "Route Table ID",
              "type": "text"
            }
          ]
        },
        "routeTableId": "rtb-02e5b59e28181011c",
        "vpcId": "vpc-0eb8eab8fc060589d",
        "isContainer": false,
        "size": {
          "width": 120,
          "height": 88
        },
        "config": {
          "originalType": "AWS::EC2::RouteTable",
          "region": "0eb8eab8fc060589d",
          "vpcId": "vpc-0eb8eab8fc060589d",
          "ownerId": "720150001470"
        },
        "nestingDepth": 2,
        "parentId": "vpc-vpc-0eb8eab8fc060589d"
      },
      "width": 120,
      "height": 88
    },
    {
      "id": "rt-rtb-066fcdc4ec8cdb638",
      "type": "resourceNode",
      "position": {
        "x": 1800,
        "y": 528
      },
      "data": {
        "label": "rtb-066fcdc4ec8cdb638",
        "resourceType": {
          "id": "routetable",
          "name": "Route Table",
          "category": "networking",
          "icon": "vpc",
          "description": "Route Table",
          "color": "#8C4FFF",
          "editableAttributes": [
            {
              "key": "label",
              "label": "Route Table ID",
              "type": "text"
            }
          ]
        },
        "routeTableId": "rtb-066fcdc4ec8cdb638",
        "vpcId": "vpc-0eb8eab8fc060589d",
        "isContainer": false,
        "size": {
          "width": 120,
          "height": 88
        },
        "config": {
          "originalType": "AWS::EC2::RouteTable",
          "region": "0eb8eab8fc060589d",
          "vpcId": "vpc-0eb8eab8fc060589d",
          "ownerId": "720150001470"
        },
        "nestingDepth": 2,
        "parentId": "vpc-vpc-0eb8eab8fc060589d"
      },
      "width": 120,
      "height": 88
    },
    {
      "id": "sg-sg-0c7910417aebd89b9",
      "type": "resourceNode",
      "position": {
        "x": 0,
        "y": 0
      },
      "data": {
        "label": "blazeops-agent-staging-agent",
        "resourceType": {
          "id": "securityGroup",
          "name": "Security Group",
          "category": "security",
          "icon": "waf",
          "description": "Security Group",
          "color": "#DD344C",
          "editableAttributes": [
            {
              "key": "label",
              "label": "SG Name",
              "type": "text"
            }
          ]
        },
        "groupId": "sg-0c7910417aebd89b9",
        "groupName": "blazeops-agent-staging-agent",
        "vpcId": "vpc-06cc31a57a405feb8",
        "description": "Allow SSH and HTTP access",
        "inboundRules": 3,
        "outboundRules": 1,
        "isContainer": true,
        "size": {
          "width": 150,
          "height": 80
        },
        "config": {
          "originalType": "AWS::EC2::SecurityGroup",
          "region": "06cc31a57a405feb8",
          "ownerId": "720150001470",
          "vpc": "vpc-06cc31a57a405feb8",
          "groupName": "blazeops-agent-staging-agent"
        },
        "nestingDepth": 2,
        "parentId": "vpc-vpc-06cc31a57a405feb8"
      },
      "width": 150,
      "height": 80
    }
  ],
  "edges": [
    {
      "id": "vpc-to-subnet-vpc-vpc-0010db00d5f9b6d24-subnet-subnet-0d7e95372896d77e8",
      "source": "vpc-vpc-0010db00d5f9b6d24",
      "target": "subnet-subnet-0d7e95372896d77e8",
      "animated": true,
      "type": "smoothstep",
      "style": {
        "stroke": "#8C4FFF",
        "strokeWidth": 2
      }
    },
    {
      "id": "vpc-to-subnet-vpc-vpc-0010db00d5f9b6d24-subnet-subnet-0f74cb72353a2b237",
      "source": "vpc-vpc-0010db00d5f9b6d24",
      "target": "subnet-subnet-0f74cb72353a2b237",
      "animated": true,
      "type": "smoothstep",
      "style": {
        "stroke": "#8C4FFF",
        "strokeWidth": 2
      },
      "data": {
        "waypoints": [
          {
            "x": 770.0,
            "y": 290.0
          },
          {
            "x": 770.0,
            "y": 400.0
          }
        ]
      }
    },
    {
      "id": "vpc-to-subnet-vpc-vpc-0010db00d5f9b6d24-subnet-subnet-0caaa7cee2f392f8d",
      "source": "vpc-vpc-0010db00d5f9b6d24",
      "target": "subnet-subnet-0caaa7cee2f392f8d",
      "animated": true,
      "type": "smoothstep",
      "style": {
        "stroke": "#8C4FFF",
        "strokeWidth": 2
      },
      "data": {
        "waypoints": [
          {
            "x": 770.0,
            "y": 290.0
          },
          {
            "x": 770.0,
            "y": 500.0
          }
        ]
      }
    },
    {
      "id": "vpc-to-subnet-vpc-vpc-0eb8eab8fc060589d-subnet-subnet-0cc22aef01a024a4a",
      "source": "vpc-vpc-0eb8eab8fc060589d",
      "target": "subnet-subnet-0cc22aef01a024a4a",
      "animated": true,
      "type": "smoothstep",
      "style": {
        "stroke": "#8C4FFF",
        "strokeWidth": 2
      }
    },
    {
      "id": "vpc-to-subnet-vpc-vpc-0eb8eab8fc060589d-subnet-subnet-01c723a4e0cd68d4f",
      "source": "vpc-vpc-0eb8eab8fc060589d",
      "target": "subnet-subnet-01c723a4e0cd68d4f",
      "animated": true,
      "type": "smoothstep",
      "style": {
        "stroke": "#8C4FFF",
        "strokeWidth": 2
      },
      "data": {
        "waypoints": [
          {
            "x": 1670.0,
            "y": 290.0
          },
          {
            "x": 1670.0,
            "y": 400.0
          }
        ]
      }
    },
    {
      "id": "vpc-to-subnet-vpc-vpc-06cc31a57a405feb8-subnet-subnet-0da1a05dfc8b55dc3",
      "source": "vpc-vpc-06cc31a57a405feb8",
      "target": "subnet-subnet-0da1a05dfc8b55dc3",
      "animated": true,
      "type": "smoothstep",
      "style": {
        "stroke": "#8C4FFF",
        "strokeWidth": 2
      }
    },
    {
      "id": "vpc-to-subnet-vpc-vpc-06cc31a57a405feb8-subnet-subnet-09a9db2e951c22a88",
      "source": "vpc-vpc-06cc31a57a405feb8",
      "target": "subnet-subnet-09a9db2e951c22a88",
      "animated": true,
      "type": "smoothstep",
      "style": {
        "stroke": "#8C4FFF",
        "strokeWidth": 2
      },
      "data": {
        "waypoints": [
          {
            "x": 320.0,
            "y": 290.0
          },
          {
            "x": 320.0,
            "y": 400.0
          }
        ]
      }
    },
    {
      "id": "vpc-to-subnet-vpc-vpc-0b71e8dcdd9a40ef8-subnet-subnet-0381aa2076a4bb590",
      "source": "vpc-vpc-0b71e8dcdd9a40ef8",
      "target": "subnet-subnet-0381aa2076a4bb590",
      "animated": true,
      "type": "smoothstep",
      "style": {
        "stroke": "#8C4FFF",
        "strokeWidth": 2
      }
    },
    {
      "id": "vpc-to-subnet-vpc-vpc-0b71e8dcdd9a40ef8-subnet-subnet-03f6049180d037062",
      "source": "vpc-vpc-0b71e8dcdd9a40ef8",
      "target": "subnet-subnet-03f6049180d037062",
      "animated": true,
      "type": "smoothstep",
      "style": {
        "stroke": "#8C4FFF",
        "strokeWidth": 2
      },
      "data": {
        "waypoints": [
          {
            "x": 1220.0,
            "y": 290.0
          },
          {
            "x": 1220.0,
            "y": 400.0
          }
        ]
      }
    },
    {
      "id": "subnet-to-instance-subnet-subnet-0da1a05dfc8b55dc3-instance-i-0525e04aaef702279",
      "source": "subnet-subnet-0da1a05dfc8b55dc3",
      "target": "instance-i-0525e04aaef702279",
      "animated": true,
      "type": "smoothstep",
      "style": {
        "stroke": "#FF9900",
        "strokeWidth": 2
      },
      "data": {
        "waypoints": [
          {
            "x": 220.0,
            "y": 300.0
          },
          {
            "x": 220.0,
            "y": 334.0
          }
        ]
      }
    },
    {
      "id": "rt-to-subnet-rt-rtb-051150827cea9acd3-subnet-subnet-03f6049180d037062",
      "source": "rt-rtb-051150827cea9acd3",
      "target": "subnet-subnet-03f6049180d037062",
      "animated": true,
      "type": "smoothstep",
      "style": {
        "stroke": "#FFA000",
        "strokeWidth": 2,
        "strokeDasharray": "4,4"
      },
      "data": {
        "waypoints": [
          {
            "x": 1100.0,
            "y": 370.0
          },
          {
            "x": 1140.0,
            "y": 370.0
          }
        ]
      }
    },
    {
      "id": "rt-to-subnet-rt-rtb-051150827cea9acd3-subnet-subnet-0381aa2076a4bb590",
      "source": "rt-rtb-051150827cea9acd3",
      "target": "subnet-subnet-0381aa2076a4bb590",
      "animated": true,
      "type": "smoothstep",
      "style": {
        "stroke": "#FFA000",
        "strokeWidth": 2,
        "strokeDasharray": "4,4"
      },
      "data": {
        "waypoints": [
          {
            "x": 1100.0,
            "y": 370.0
          },
          {
            "x": 1140.0,
            "y": 370.0
          }
        ]
      }
    },
    {
      "id": "rt-to-subnet-rt-rtb-0f5539d37304dfe0a-subnet-subnet-09a9db2e951c22a88",
      "source": "rt-rtb-0f5539d37304dfe0a",
      "target": "subnet-subnet-09a9db2e951c22a88",
      "animated": true,
      "type": "smoothstep",
      "style": {
        "stroke": "#FFA000",
        "strokeWidth": 2,
        "strokeDasharray": "4,4"
      },
      "data": {
        "waypoints": [
          {
            "x": 200.0,
            "y": 370.0
          },
          {
            "x": 240.0,
            "y": 370.0
          }
        ]
      }
    },
    {
      "id": "rt-to-subnet-rt-rtb-0f5539d37304dfe0a-subnet-subnet-0da1a05dfc8b55dc3",
      "source": "rt-rtb-0f5539d37304dfe0a",
      "target": "subnet-subnet-0da1a05dfc8b55dc3",
      "animated": true,
      "type": "smoothstep",
      "style": {
        "stroke": "#FFA000",
        "strokeWidth": 2,
        "strokeDasharray": "4,4"
      },
      "data": {
        "waypoints": [
          {
            "x": 200.0,
            "y": 370.0
          },
          {
            "x": 240.0,
            "y": 370.0
          }
        ]
      }
    },
    {
      "id": "rt-to-subnet-rt-rtb-066fcdc4ec8cdb638-subnet-subnet-0cc22aef01a024a4a",
      "source": "rt-rtb-066fcdc4ec8cdb638",
      "target": "subnet-subnet-0cc22aef01a024a4a",
      "animated": true,
      "type": "smoothstep",
      "style": {
        "stroke": "#FFA000",
        "strokeWidth": 2,
        "strokeDasharray": "4,4"
      },
      "data": {
        "waypoints": [
          {
            "x": 1550.0,
            "y": 370.0
          },
          {
            "x": 1590.0,
            "y": 370.0
          }
        ]
      }
    },
    {
      "id": "rt-to-subnet-rt-rtb-066fcdc4ec8cdb638-subnet-subnet-01c723a4e0cd68d4f",
      "source": "rt-rtb-066fcdc4ec8cdb638",
      "target": "subnet-subnet-01c723a4e0cd68d4f",
      "animated": true,
      "type": "smoothstep",
      "style": {
        "stroke": "#FFA000",
        "strokeWidth": 2,
        "strokeDasharray": "4,4"
      },
      "data": {
        "waypoints": [
          {
            "x": 1550.0,
            "y": 370.0
          },
          {
            "x": 1590.0,
            "y": 370.0
          }
        ]
      }
    },
    {
      "id": "sg-to-instance-sg-sg-0c7910417aebd89b9-instance-i-0525e04aaef702279",
      "source": "sg-sg-0c7910417aebd89b9",
      "target": "instance-i-0525e04aaef702279",
      "animated": true,
      "type": "smoothstep",
      "style": {
        "stroke": "#DD344C",
        "strokeWidth": 1,
        "strokeDasharray": "5,5"
      },
      "data": {
        "waypoints": [
          {
            "x": 130.0,
            "y": 40.0
          },
          {
            "x": 130.0,
            "y": 334.0
          }
        ]
      }
    },
    {
      "id": "instance-in-subnet-instance-i-0525e04aaef702279-subnet-subnet-0da1a05dfc8b55dc3",
      "source": "instance-i-0525e04aaef702279",
      "target": "subnet-subnet-0da1a05dfc8b55dc3",
      "animated": true,
      "type": "smoothstep",
      "style": {
        "stroke": "#999999",
        "strokeWidth": 1
      },
      "data": {
        "waypoints": [
          {
            "x": 220.0,
            "y": 334.0
          },
          {
            "x": 220.0,
            "y": 300.0
          }
        ]
      }
    }
  ]
}